[{"id":1,"name":"Thankama patch","releaseYear":2069,"duration":80},{"id":2,"name":"Thankama patch","releaseYear":2069,"duration":80},{"id":6,"name":"yaarada version 2","releaseYear":1998,"duration":90},{"id":7,"name":"Thankama patch","releaseYear":2069,"duration":80},{"id":8},{"id":9,"name":"Thankama patch","releaseYear":2069,"duration":80},{"id":10,"name":"Thankama patch","releaseYear":2069,"duration":80},{"id":11},{"id":12,"name":"yaarada version 2","releaseYear":1998,"duration":90},{"id":13,"releaseYear":1998,"duration":90},{"id":14,"releaseYear":1998,"duration":90},{"id":15,"name":"govinda version 2","releaseYear":1998,"duration":90},{"id":16,"name":"govinda version 2","releaseYear":1998,"duration":90},{"id":17,"name":"govinda version 2","releaseYear":1998,"duration":90}]